pysquareblob/__init__.py
pysquareblob/_http/__init__.py
pysquareblob/_http/endpoints.py
pysquareblob/_http/http.py
pysquareblob/client.py
pysquareblob/data.py
pysquareblob/errors.py
pysquareblob/utils/__init__.py
pysquareblob/utils/cache.py
pysquareblob/utils/file.py
pysquareblob/utils/logs.py
pysquareblob-2.1.0.dist-info/licenses/LICENSE
pysquareblob-2.1.0.dist-info/METADATA
pysquareblob-2.1.0.dist-info/WHEEL
pysquareblob-2.1.0.dist-info/RECORD
