Metadata-Version: 2.4
Name: pysquareblob
Version: 2.1.0
Summary: This project is just a simple way to interact with Square Cloud Blob service
License-File: LICENSE
Author: Jhonatan Jeferson
Author-email: jhonatanjefersonoliveira@gmail.com
Requires-Python: >=3.11.0,<4.0.0
Classifier: Programming Language :: Python :: 3
Classifier: Programming Language :: Python :: 3.11
Classifier: Programming Language :: Python :: 3.12
Classifier: Programming Language :: Python :: 3.13
Classifier: Programming Language :: Python :: 3.14
Requires-Dist: aiohttp (>=3.11.10,<4.0.0)
